pyattr/__init__.py
pyattr-1.4.6.dist-info/LICENSE
pyattr-1.4.6.dist-info/METADATA
pyattr-1.4.6.dist-info/WHEEL
pyattr-1.4.6.dist-info/top_level.txt
pyattr-1.4.6.dist-info/RECORD
