Metadata-Version: 2.1
Name: pyattr
Version: 1.4.6
Summary: Proper access modifiers for Python classes.
Home-page: https://github.com/skifli/pyattr
Author: skifli
License: MIT
Project-URL: Documentation, https://github.com/skifli/pyattr#example
Project-URL: Source, https://github.com/skifli/pyattr
Classifier: Development Status :: 5 - Production/Stable
Classifier: Intended Audience :: Developers
Classifier: License :: OSI Approved :: MIT License
Classifier: Natural Language :: English
Classifier: Operating System :: OS Independent
Classifier: Programming Language :: Python :: 3
License-File: LICENSE
